README.rst
setup.py
markdown_blockdiag/__init__.py
markdown_blockdiag/extension.py
markdown_blockdiag/parser.py
markdown_blockdiag/utils.py
markdown_blockdiag.egg-info/PKG-INFO
markdown_blockdiag.egg-info/SOURCES.txt
markdown_blockdiag.egg-info/dependency_links.txt
markdown_blockdiag.egg-info/requires.txt
markdown_blockdiag.egg-info/top_level.txt
tests/__init__.py
tests/test_blockdiag.py