Metadata-Version: 1.0
Name: markdown-blockdiag
Version: 0.1.1
Summary: blockdiag extension for Python Markdown
Home-page: https://github.com/gisce/markdown-blockdiag
Author: GISCE-TI, S.L.
Author-email: devel@gisce.net
License: MIT
Platform: UNKNOWN
